naughty_parrot/__init__.py
naughty_parrot/bodygram_preprocessor.py
naughty_parrot/preprocessor.py
naughty_parrot/calculation_recorder/__init__.py
naughty_parrot/calculation_recorder/calculation_recorder.py
naughty_parrot/encoder_decoder/__init__.py
naughty_parrot/encoder_decoder/encoder_decoder.py
naughty_parrot-0.0.4.dist-info/LICENSE.txt
naughty_parrot-0.0.4.dist-info/METADATA
naughty_parrot-0.0.4.dist-info/WHEEL
naughty_parrot-0.0.4.dist-info/top_level.txt
naughty_parrot-0.0.4.dist-info/RECORD
