Metadata-Version: 2.1
Name: naughty-parrot
Version: 0.0.4
Summary: a simple image preprocess tool
Home-page: https://github.com/uyuutosa/naughty_parrot
Author: uyuutosa
Author-email: sayu819@gmail.com
License: MIT
Keywords: preprocess
Platform: UNKNOWN
Classifier: Programming Language :: Python :: 3.6
Requires-Dist: pillow
